sgf_parser/__init__.py
sgf_parser/datetime_parser.py
sgf_parser/parser.py
sgf_parser/models/__init__.py
sgf_parser/models/method.py
sgf_parser/models/method_cpt.py
sgf_parser/models/method_dp.py
sgf_parser/models/method_dt.py
sgf_parser/models/method_rp.py
sgf_parser/models/method_slb.py
sgf_parser/models/method_srs.py
sgf_parser/models/method_sti.py
sgf_parser/models/method_svt.py
sgf_parser/models/method_tot.py
sgf_parser/models/method_tr.py
sgf_parser/models/method_type.py
sgf_parser/models/method_wst.py
sgf_parser/models/types.py
sgf_parser-0.0.9.dist-info/METADATA
sgf_parser-0.0.9.dist-info/WHEEL
sgf_parser-0.0.9.dist-info/licenses/LICENSE
sgf_parser-0.0.9.dist-info/RECORD
