Metadata-Version: 2.4
Name: sgf-parser
Version: 0.0.9
Summary: Parser for the Swedish Geotechnical Society / Svenska Geotekniska Föreningen (SGF) data format
Project-URL: homepage, https://github.com/norwegian-geotechnical-institute/sgf-parser
Project-URL: repository, https://github.com/norwegian-geotechnical-institute/sgf-parser
Author-email: Jostein Leira <jostein@leira.net>
Maintainer-email: Jostein Leira <jostein@leira.net>
License-File: LICENSE
Classifier: Development Status :: 5 - Production/Stable
Classifier: License :: OSI Approved :: MIT License
Classifier: Operating System :: OS Independent
Classifier: Programming Language :: Python :: 3
Classifier: Topic :: Scientific/Engineering :: GIS
Requires-Python: <4,>=3.11
Requires-Dist: pydantic>=2.10
Requires-Dist: python-dateutil>=2.9.0.post0
Requires-Dist: types-python-dateutil>=2.9
